headless_ida_mcp_server/__init__.py
headless_ida_mcp_server/__main__.py
headless_ida_mcp_server/helper.py
headless_ida_mcp_server/logger.py
headless_ida_mcp_server/server.py
mseep_headless_ida_mcp_server-0.1.4.dist-info/METADATA
mseep_headless_ida_mcp_server-0.1.4.dist-info/WHEEL
mseep_headless_ida_mcp_server-0.1.4.dist-info/entry_points.txt
mseep_headless_ida_mcp_server-0.1.4.dist-info/top_level.txt
mseep_headless_ida_mcp_server-0.1.4.dist-info/RECORD
